{
  "track": "hibari",
  "metric": "tonnetz",
  "n_cycles": 18,
  "pitch_range": [
    40,
    88
  ],
  "n_candidates": 1000,
  "orig_mean_dissonance": 0.264,
  "orig_n_pitch_classes": 7,
  "experiments": {
    "baseline": {
      "harmony_mode": null,
      "note_dist_error": 4.3451,
      "cycle_dist_error": 1.3491,
      "consonance_score": 0.0,
      "interval_error": 0.0,
      "total_cost": 2.8471,
      "elapsed_s": 5.9,
      "n_generated": 3706,
      "new_pitches": [
        41,
        44,
        51,
        52,
        55,
        58,
        64,
        66,
        68,
        70,
        73,
        75,
        82,
        84,
        85,
        86,
        88
      ],
      "harmony_mean_dissonance": 0.4121031746031746,
      "harmony_max_dissonance": 0.6333333333333333,
      "harmony_min_dissonance": 0.15,
      "harmony_best_scale_match": 0.7,
      "harmony_best_scale_name": "C# major",
      "harmony_pitch_classes_used": [
        0,
        1,
        2,
        3,
        4,
        5,
        6,
        7,
        8,
        10
      ],
      "harmony_n_pitch_classes": 10
    },
    "scale_major": {
      "harmony_mode": "scale",
      "note_dist_error": 3.5169,
      "cycle_dist_error": 1.4771,
      "consonance_score": 0.0,
      "interval_error": 0.0,
      "total_cost": 2.497,
      "elapsed_s": 3.5,
      "n_generated": 3706,
      "new_pitches": [
        40,
        41,
        47,
        52,
        59,
        60,
        62,
        64,
        65,
        67,
        69,
        71,
        72,
        74,
        76,
        77,
        81
      ],
      "harmony_mean_dissonance": 0.3614153439153439,
      "harmony_max_dissonance": 0.5499999999999999,
      "harmony_min_dissonance": 0.16666666666666666,
      "harmony_best_scale_match": 1.0,
      "harmony_best_scale_name": "C major",
      "harmony_pitch_classes_used": [
        0,
        2,
        4,
        5,
        7,
        9,
        11
      ],
      "harmony_n_pitch_classes": 7,
      "scale_type": "major",
      "scale_root": "C",
      "pool_size": 29
    },
    "scale_minor": {
      "harmony_mode": "scale",
      "note_dist_error": 3.6776,
      "cycle_dist_error": 1.6927,
      "consonance_score": 0.0,
      "interval_error": 0.0,
      "total_cost": 2.6851,
      "elapsed_s": 4.9,
      "n_generated": 3706,
      "new_pitches": [
        40,
        42,
        47,
        52,
        59,
        61,
        63,
        64,
        66,
        68,
        69,
        71,
        73,
        75,
        76,
        78,
        81
      ],
      "harmony_mean_dissonance": 0.36334656084656086,
      "harmony_max_dissonance": 0.6666666666666666,
      "harmony_min_dissonance": 0.16666666666666666,
      "harmony_best_scale_match": 1.0,
      "harmony_best_scale_name": "E major",
      "harmony_pitch_classes_used": [
        1,
        3,
        4,
        6,
        8,
        9,
        11
      ],
      "harmony_n_pitch_classes": 7,
      "scale_type": "minor",
      "scale_root": "C#",
      "pool_size": 29
    },
    "scale_penta": {
      "harmony_mode": "scale",
      "note_dist_error": 4.3168,
      "cycle_dist_error": 1.4839,
      "consonance_score": 0.0,
      "interval_error": 0.0,
      "total_cost": 2.9004,
      "elapsed_s": 5.9,
      "n_generated": 3706,
      "new_pitches": [
        40,
        43,
        45,
        48,
        50,
        52,
        55,
        57,
        60,
        69,
        72,
        74,
        76,
        79,
        81,
        86,
        88
      ],
      "harmony_mean_dissonance": 0.213478835978836,
      "harmony_max_dissonance": 0.5333333333333333,
      "harmony_min_dissonance": 0.03333333333333333,
      "harmony_best_scale_match": 1.0,
      "harmony_best_scale_name": "C major",
      "harmony_pitch_classes_used": [
        0,
        2,
        4,
        7,
        9
      ],
      "harmony_n_pitch_classes": 5,
      "scale_type": "pentatonic",
      "scale_root": "C",
      "pool_size": 21
    },
    "consonance": {
      "harmony_mode": "consonance",
      "note_dist_error": 4.3451,
      "cycle_dist_error": 1.3491,
      "consonance_score": 0.4121,
      "interval_error": 0.0,
      "total_cost": 2.9708,
      "elapsed_s": 5.8,
      "n_generated": 3706,
      "new_pitches": [
        41,
        44,
        51,
        52,
        55,
        58,
        64,
        66,
        68,
        70,
        73,
        75,
        82,
        84,
        85,
        86,
        88
      ],
      "harmony_mean_dissonance": 0.4121031746031746,
      "harmony_max_dissonance": 0.6333333333333333,
      "harmony_min_dissonance": 0.15,
      "harmony_best_scale_match": 0.7,
      "harmony_best_scale_name": "C# major",
      "harmony_pitch_classes_used": [
        0,
        1,
        2,
        3,
        4,
        5,
        6,
        7,
        8,
        10
      ],
      "harmony_n_pitch_classes": 10
    },
    "interval": {
      "harmony_mode": "interval",
      "note_dist_error": 4.3526,
      "cycle_dist_error": 1.344,
      "consonance_score": 0.0,
      "interval_error": 0.8582,
      "total_cost": 3.1058,
      "elapsed_s": 8.7,
      "n_generated": 3706,
      "new_pitches": [
        42,
        43,
        45,
        49,
        50,
        51,
        52,
        54,
        56,
        60,
        61,
        63,
        70,
        76,
        78,
        83,
        87
      ],
      "harmony_mean_dissonance": 0.43674603174603166,
      "harmony_max_dissonance": 0.63,
      "harmony_min_dissonance": 0.19999999999999998,
      "harmony_best_scale_match": 0.6363636363636364,
      "harmony_best_scale_name": "D major",
      "harmony_pitch_classes_used": [
        0,
        1,
        2,
        3,
        4,
        6,
        7,
        8,
        9,
        10,
        11
      ],
      "harmony_n_pitch_classes": 11
    },
    "all_major": {
      "harmony_mode": "all",
      "note_dist_error": 3.5169,
      "cycle_dist_error": 1.4771,
      "consonance_score": 0.3614,
      "interval_error": 0.4669,
      "total_cost": 2.7455,
      "elapsed_s": 5.4,
      "n_generated": 3706,
      "new_pitches": [
        40,
        41,
        47,
        52,
        59,
        60,
        62,
        64,
        65,
        67,
        69,
        71,
        72,
        74,
        76,
        77,
        81
      ],
      "harmony_mean_dissonance": 0.3614153439153439,
      "harmony_max_dissonance": 0.5499999999999999,
      "harmony_min_dissonance": 0.16666666666666666,
      "harmony_best_scale_match": 1.0,
      "harmony_best_scale_name": "C major",
      "harmony_pitch_classes_used": [
        0,
        2,
        4,
        5,
        7,
        9,
        11
      ],
      "harmony_n_pitch_classes": 7,
      "scale_type": "major",
      "scale_root": "C",
      "pool_size": 29
    },
    "all_penta": {
      "harmony_mode": "all",
      "note_dist_error": 4.3168,
      "cycle_dist_error": 1.4839,
      "consonance_score": 0.2135,
      "interval_error": 0.8235,
      "total_cost": 3.2115,
      "elapsed_s": 6.2,
      "n_generated": 3706,
      "new_pitches": [
        40,
        43,
        45,
        48,
        50,
        52,
        55,
        57,
        60,
        69,
        72,
        74,
        76,
        79,
        81,
        86,
        88
      ],
      "harmony_mean_dissonance": 0.213478835978836,
      "harmony_max_dissonance": 0.5333333333333333,
      "harmony_min_dissonance": 0.03333333333333333,
      "harmony_best_scale_match": 1.0,
      "harmony_best_scale_name": "C major",
      "harmony_pitch_classes_used": [
        0,
        2,
        4,
        7,
        9
      ],
      "harmony_n_pitch_classes": 5,
      "scale_type": "pentatonic",
      "scale_root": "C",
      "pool_size": 21
    }
  }
}